gurush/__init__.py
gurush/config.py
gurush/constants.py
gurush/kernel.py
gurush/assets/config.yaml
gurush-0.2.8.dist-info/METADATA
gurush-0.2.8.dist-info/WHEEL
gurush-0.2.8.dist-info/entry_points.txt
gurush-0.2.8.dist-info/licenses/LICENSE
gurush-0.2.8.dist-info/RECORD
