Metadata-Version: 2.4
Name: gurush
Version: 0.2.8
Summary: Linux Shell AI Agent.
Project-URL: homepage, https://github.com/antrax2024/gurush
Project-URL: Repository, https://github.com/antrax2024/gurush
Author-email: Antrax <fredcox@gmail.com>
License: MIT
License-File: LICENSE
Requires-Python: >=3.13
Requires-Dist: confz>=2.1.0
Requires-Dist: inquirerpy>=0.3.4
Requires-Dist: langchain-openai>=0.3.16
Requires-Dist: langchain>=0.3.25
Requires-Dist: rich>=14.0.0
